{
	"info": {
		"_postman_id": "6843bcd0-a27b-402b-a7e8-282aa5cc3820",
		"name": "COMMOV Remoto",
		"schema": "https://schema.getpostman.com/json/collection/v2.1.0/collection.json"
	},
	"item": [
		{
			"name": "User",
			"item": [
				{
					"name": "Get All Users",
					"request": {
						"method": "GET",
						"header": [],
						"url": {
							"raw": "http://commovgabriel2021.000webhostapp.com/myslim/api/user/getAllUsers",
							"protocol": "http",
							"host": [
								"commovgabriel2021",
								"000webhostapp",
								"com"
							],
							"path": [
								"myslim",
								"api",
								"user",
								"getAllUsers"
							]
						}
					},
					"response": []
				},
				{
					"name": "Get User By ID",
					"request": {
						"method": "GET",
						"header": [],
						"url": {
							"raw": "http://commovgabriel2021.000webhostapp.com/myslim/api/user/getUser/1",
							"protocol": "http",
							"host": [
								"commovgabriel2021",
								"000webhostapp",
								"com"
							],
							"path": [
								"myslim",
								"api",
								"user",
								"getUser",
								"1"
							]
						}
					},
					"response": []
				},
				{
					"name": "Get User By Username and Pasword",
					"request": {
						"method": "GET",
						"header": [],
						"url": {
							"raw": "http://commovgabriel2021.000webhostapp.com/myslim/api/user/login/gabrielSousa&&1243",
							"protocol": "http",
							"host": [
								"commovgabriel2021",
								"000webhostapp",
								"com"
							],
							"path": [
								"myslim",
								"api",
								"user",
								"login",
								"gabrielSousa&&1243"
							]
						}
					},
					"response": []
				},
				{
					"name": "Add User",
					"request": {
						"method": "POST",
						"header": [],
						"body": {
							"mode": "formdata",
							"formdata": [
								{
									"key": "username",
									"value": "testeRemoto",
									"type": "text"
								},
								{
									"key": "first_name",
									"value": "Lima",
									"type": "text"
								},
								{
									"key": "last_name",
									"value": "Rodrigues",
									"type": "text"
								},
								{
									"key": "email",
									"value": "limoeiro@gmail.com",
									"type": "text"
								},
								{
									"key": "password",
									"value": "1243",
									"type": "text"
								},
								{
									"key": "notification",
									"value": "0",
									"type": "text"
								}
							]
						},
						"url": {
							"raw": "http://commovgabriel2021.000webhostapp.com/myslim/api/user/addNewUser",
							"protocol": "http",
							"host": [
								"commovgabriel2021",
								"000webhostapp",
								"com"
							],
							"path": [
								"myslim",
								"api",
								"user",
								"addNewUser"
							]
						}
					},
					"response": []
				},
				{
					"name": "Put User  By ID",
					"request": {
						"method": "PUT",
						"header": [],
						"body": {
							"mode": "urlencoded",
							"urlencoded": [
								{
									"key": "first_name",
									"value": "Gabriel",
									"type": "text"
								},
								{
									"key": "last_name",
									"value": "Sousa",
									"type": "text"
								},
								{
									"key": "email",
									"value": "gabrielsousa@ipvc.pt",
									"type": "text"
								},
								{
									"key": "notifications",
									"value": "0",
									"type": "text"
								}
							]
						},
						"url": {
							"raw": "http://commovgabriel2021.000webhostapp.com/myslim/api/user/changeUserInfo/1",
							"protocol": "http",
							"host": [
								"commovgabriel2021",
								"000webhostapp",
								"com"
							],
							"path": [
								"myslim",
								"api",
								"user",
								"changeUserInfo",
								"1"
							],
							"query": [
								{
									"key": "first_name",
									"value": "Gabriel",
									"disabled": true
								},
								{
									"key": "last_name",
									"value": "Sousa",
									"disabled": true
								},
								{
									"key": "email",
									"value": "gabrielsousa@ipvc.pt",
									"disabled": true
								},
								{
									"key": "notifications",
									"value": "0",
									"disabled": true
								}
							]
						}
					},
					"response": []
				}
			]
		},
		{
			"name": "Ocorrency",
			"item": [
				{
					"name": "Get All Ocorrences",
					"request": {
						"method": "GET",
						"header": [],
						"url": {
							"raw": "http://commovgabriel2021.000webhostapp.com/myslim/api/ocorrency/getAllOcorrences",
							"protocol": "http",
							"host": [
								"commovgabriel2021",
								"000webhostapp",
								"com"
							],
							"path": [
								"myslim",
								"api",
								"ocorrency",
								"getAllOcorrences"
							]
						}
					},
					"response": []
				},
				{
					"name": "Get Ocorrency By Id",
					"request": {
						"method": "GET",
						"header": [],
						"url": {
							"raw": "http://commovgabriel2021.000webhostapp.com/myslim/api/ocorrency/getOcorrency/2",
							"protocol": "http",
							"host": [
								"commovgabriel2021",
								"000webhostapp",
								"com"
							],
							"path": [
								"myslim",
								"api",
								"ocorrency",
								"getOcorrency",
								"2"
							]
						}
					},
					"response": []
				},
				{
					"name": "Get All Ocorrences By Category",
					"request": {
						"method": "GET",
						"header": [],
						"url": {
							"raw": "http://commovgabriel2021.000webhostapp.com/myslim/api/ocorrency/getAllOcorrencesByCategory/1",
							"protocol": "http",
							"host": [
								"commovgabriel2021",
								"000webhostapp",
								"com"
							],
							"path": [
								"myslim",
								"api",
								"ocorrency",
								"getAllOcorrencesByCategory",
								"1"
							]
						}
					},
					"response": []
				},
				{
					"name": "Get Ocorrences By User",
					"request": {
						"method": "GET",
						"header": [],
						"url": {
							"raw": "http://commovgabriel2021.000webhostapp.com/myslim/api/ocorrency/ocorrencyByUser/1",
							"protocol": "http",
							"host": [
								"commovgabriel2021",
								"000webhostapp",
								"com"
							],
							"path": [
								"myslim",
								"api",
								"ocorrency",
								"ocorrencyByUser",
								"1"
							]
						}
					},
					"response": []
				},
				{
					"name": "Put Ocorrency By Id",
					"request": {
						"method": "PUT",
						"header": [],
						"body": {
							"mode": "urlencoded",
							"urlencoded": [
								{
									"key": "category_id",
									"value": "1",
									"type": "text"
								},
								{
									"key": "street",
									"value": "morada xpto",
									"type": "text"
								},
								{
									"key": "reference_point",
									"value": "ha beira das bananas",
									"type": "text"
								},
								{
									"key": "description",
									"value": "ta tudo mesmo muito partido",
									"type": "text"
								}
							]
						},
						"url": {
							"raw": "http://commovgabriel2021.000webhostapp.com/myslim/api/ocorrency/changeOcorrencyInfo/3",
							"protocol": "http",
							"host": [
								"commovgabriel2021",
								"000webhostapp",
								"com"
							],
							"path": [
								"myslim",
								"api",
								"ocorrency",
								"changeOcorrencyInfo",
								"3"
							]
						}
					},
					"response": []
				},
				{
					"name": "Add Ocorrency",
					"request": {
						"method": "POST",
						"header": [],
						"body": {
							"mode": "formdata",
							"formdata": [
								{
									"key": "category_id",
									"value": "1",
									"type": "text"
								},
								{
									"key": "user_id",
									"value": "1",
									"type": "text"
								},
								{
									"key": "foto",
									"value": "FotoRemoto",
									"type": "text"
								},
								{
									"key": "street",
									"value": "Rua remota",
									"type": "text"
								},
								{
									"key": "reference_point",
									"value": "webhost",
									"type": "text"
								},
								{
									"key": "description",
									"value": "ewre",
									"type": "text"
								},
								{
									"key": "latitude",
									"value": "123",
									"type": "text"
								},
								{
									"key": "longitude",
									"value": "123",
									"type": "text"
								},
								{
									"key": "date",
									"value": "2021-03-14 21:10:00",
									"type": "text"
								}
							]
						},
						"url": {
							"raw": "http://commovgabriel2021.000webhostapp.com/myslim/api/ocorrency/addNewOcorrency",
							"protocol": "http",
							"host": [
								"commovgabriel2021",
								"000webhostapp",
								"com"
							],
							"path": [
								"myslim",
								"api",
								"ocorrency",
								"addNewOcorrency"
							]
						}
					},
					"response": []
				},
				{
					"name": "Delete Ocorrency By Id",
					"request": {
						"method": "DELETE",
						"header": [],
						"url": {
							"raw": "http://commovgabriel2021.000webhostapp.com/myslim/api/ocorrency/getOcorrency/3",
							"protocol": "http",
							"host": [
								"commovgabriel2021",
								"000webhostapp",
								"com"
							],
							"path": [
								"myslim",
								"api",
								"ocorrency",
								"getOcorrency",
								"3"
							]
						}
					},
					"response": []
				}
			]
		}
	]
}